{
  "黄浦区": ["121.48","31.23"],
  "徐汇区": ["121.44","31.19"],
  "长宁区": ["121.42","31.22"],
  "静安区": ["121.45","31.23"],
  "普陀区": ["121.40","31.25"],
  "虹口区": ["121.51","31.26"],
  "杨浦区": ["121.53","31.26"],
  "闵行区": ["121.38","31.11"],
  "宝山区": ["121.49","31.41"],
  "嘉定区": ["121.27","31.38"],
  "浦东新区": ["121.54","31.22"],
  "金山区": ["121.34","30.74"],
  "松江区": ["121.23","31.03"],
  "青浦区": ["121.12","31.15"],
  "奉贤区": ["121.47","30.92"],
  "虎丘区": ["120.57","31.30"],
  "姑苏区": ["120.62","31.31"],
  "相城区": ["120.64","31.37"],
  "吴中区": ["120.63","31.26"],
  "吴江区": ["120.65","31.14"],
  "常熟市": ["120.75","31.65"],
  "张家港市": ["120.56","31.88"],
  "昆山市": ["120.98","31.38"],
  "太仓市": ["121.13","31.46"],
  "锡山区": ["120.39","31.60"],
  "惠山区": ["120.30","31.68"],
  "梁溪区": ["120.31","31.56"],
  "新吴区": ["120.43","31.51"],
  "滨湖区": ["120.28","31.53"],
  "宜兴市": ["119.82","31.34"],
  "江阴市": ["120.28","31.92"],
  "新北区": ["119.97","31.83"],
  "钟楼区": ["119.90","31.80"],
  "天宁区": ["119.97","31.78"],
  "武进区": ["119.94","31.70"],
  "金坛区": ["119.60","31.72"],
  "溧阳市": ["119.48","31.41"],
  "丹阳市": ["119.60","32.01"],
  "句容市": ["119.17","31.94"],
  "丹徒区": ["119.43","32.13"],
  "京口区": ["119.47","32.20"],
  "润州区": ["119.41","32.20"],
  "秀洲区": ["120.71","30.77"],
  "南湖区": ["120.78","30.75"],
  "平湖市": ["121.02","30.68"],
  "海盐县": ["120.95","30.53"],
  "嘉善县": ["120.93","30.83"],
  "桐乡市": ["120.57","30.63"],
  "海宁市": ["120.68","30.51"],
  "吴兴区": ["120.19","30.86"],
  "南浔区": ["120.42","30.85"],
  "长兴县": ["119.91","31.03"],
  "安吉县": ["119.68","30.64"],
  "德清县": ["119.98","30.54"],
  "钱塘区": ["120.33","30.31"],
  "上城区": ["120.17","30.24"],
  "临安区": ["119.72","30.23"],
  "临平区": ["120.30","30.42"],
  "拱墅区": ["120.14","30.32"],
  "余杭区": ["119.98","30.27"],
  "西湖区": ["120.13","30.26"]
}